resume_parser_pro/__init__.py
resume_parser_pro/parser.py
resume_parser_pro/reader.py
resume_parser_pro/utils.py
resume_parser_pro/__pycache__/__init__.cpython-310.pyc
resume_parser_pro/__pycache__/reader.cpython-310.pyc
resume_parser_pro/extractors/.DS_Store
resume_parser_pro/extractors/__init__.py
resume_parser_pro/extractors/basic_fields.py
resume_parser_pro/extractors/education.py
resume_parser_pro/extractors/experience.py
resume_parser_pro/extractors/skills.py
resume_parser_pro/extractors/__pycache__/__init__.cpython-310.pyc
resume_parser_pro/extractors/__pycache__/basic_fields.cpython-310.pyc
resume_parser_pro/extractors/__pycache__/education.cpython-310.pyc
resume_parser_pro/extractors/__pycache__/experience.cpython-310.pyc
resume_parser_pro/extractors/__pycache__/skills.cpython-310.pyc
resume_parser_pro/tests/Resume_Parser_Package.code-workspace
resume_parser_pro/tests/__init__.py
resume_parser_pro/tests/test_manual_testing.py
resume_parser_pro/tests/test_parser.py
resume_parser_pro/tests/test_utils.py
resume_parser_pro/utils/__init__.py
resume_parser_pro/utils/text_sections.py
resume_parser_pro/utils/__pycache__/__init__.cpython-310.pyc
resume_parser_pro/utils/__pycache__/text_sections.cpython-310.pyc
resume_parser_pro-1.0.1.dist-info/METADATA
resume_parser_pro-1.0.1.dist-info/WHEEL
resume_parser_pro-1.0.1.dist-info/top_level.txt
resume_parser_pro-1.0.1.dist-info/RECORD
