Metadata-Version: 2.1
Name: resume_parser_pro
Version: 1.0.1
Summary: A production-grade Python package to parse PDF/DOCX resumes.
Home-page: https://github.com/kumarabhinav0905/resume_parser_pro
Author: Kumar Abhinav
Author-email: Kumar Abhinav <rushtoabhinavin@gmail.com>
Classifier: Programming Language :: Python :: 3
Classifier: License :: OSI Approved :: MIT License
Classifier: Operating System :: OS Independent
Requires-Python: >=3.6
Requires-Dist: spacy>=3.0.0
Requires-Dist: python-docx
Requires-Dist: PyPDF2
